fild_compare/__init__.py
fild_compare/compare.py
fild_compare/diff.py
fild_compare/rule_decorator.py
fild_compare/rules.py
fild_compare-0.0.4.dist-info/LICENSE
fild_compare-0.0.4.dist-info/METADATA
fild_compare-0.0.4.dist-info/WHEEL
fild_compare-0.0.4.dist-info/top_level.txt
fild_compare-0.0.4.dist-info/RECORD
