Metadata-Version: 2.1
Name: fild-compare
Version: 0.0.4
Summary: Compare objects with rules
Home-page: https://github.com/elenakulgavaya/fild-compare
Author: Elena Kulgavaya
Author-email: elena.kulgavaya@gmail.com
Project-URL: Bug Tracker, https://github.com/elenakulgavaya/fild-compare/issues
Classifier: Programming Language :: Python :: 3
Classifier: License :: OSI Approved :: MIT License
Classifier: Operating System :: OS Independent
Requires-Python: >=3.9
License-File: LICENSE
Requires-Dist: fild>=0.1.0
